goliath/__init__.py
goliath/commander.py
goliath/exceptions.py
goliath/lieutenant.py
goliath/test.py
goliath/utils.py
goliath/worker.py
goliath-0.2.3.dist-info/LICENSE
goliath-0.2.3.dist-info/METADATA
goliath-0.2.3.dist-info/WHEEL
goliath-0.2.3.dist-info/top_level.txt
goliath-0.2.3.dist-info/RECORD
