Metadata-Version: 2.1
Name: goliath
Version: 0.2.3
Summary: This package enables Python to offload sets of function calls to pools of remote worker processes.
Home-page: https://github.com/ilievartic/Goliath/
Author: Ilie Vartic, Logan Pulley, Zach Oldham, Deepan Venkatesh, Manikandan Swaminathan
Author-email: ilie.vartic@gmail.com
License: UNKNOWN
Platform: UNKNOWN
Classifier: Programming Language :: Python :: 3
Classifier: Programming Language :: Python :: 3.7
Classifier: Programming Language :: Python :: 3.8
Classifier: Operating System :: OS Independent
